<?xml version="1.0" encoding="UTF-8"?><record_update sys_domain="global" table="asmt_metric_definition">
    <asmt_metric_definition action="DELETE">
        <display>Use a Mid Server</display>
        <metric display_value="As part of the new Service Graph capability, what is the appropriate method ">4990e67b5376d2108dbe38f0a0490e14</metric>
        <normalization_input>0</normalization_input>
        <order/>
        <selected_image/>
        <sys_class_name>asmt_metric_definition</sys_class_name>
        <sys_created_by>admin</sys_created_by>
        <sys_created_on>2025-01-06 20:50:19</sys_created_on>
        <sys_domain>global</sys_domain>
        <sys_domain_path>/</sys_domain_path>
        <sys_id>5190e67b5376d2108dbe38f0a0490e2b</sys_id>
        <sys_mod_count>0</sys_mod_count>
        <sys_name>Use a Mid Server</sys_name>
        <sys_package display_value="Quizard" source="x_560335_quizard">a6b89afc537512108dbe38f0a0490e21</sys_package>
        <sys_policy/>
        <sys_scope display_value="Quizard">a6b89afc537512108dbe38f0a0490e21</sys_scope>
        <sys_update_name>asmt_metric_definition_5190e67b5376d2108dbe38f0a0490e2b</sys_update_name>
        <sys_updated_by>admin</sys_updated_by>
        <sys_updated_on>2025-01-06 20:50:19</sys_updated_on>
        <unselected_image/>
        <value>1</value>
        <x_560335_quizard_is_correct>false</x_560335_quizard_is_correct>
    </asmt_metric_definition>
    <sys_translated_text action="DELETE" query="documentkey=5190e67b5376d2108dbe38f0a0490e2b"/>
    <sys_update_version action="INSERT_OR_UPDATE">
        <action>DELETE</action>
        <application display_value="Quizard">a6b89afc537512108dbe38f0a0490e21</application>
        <file_path/>
        <instance_id>b512f08a1bde0a50c82acb7b234bcb06</instance_id>
        <instance_name>dev272638</instance_name>
        <name>asmt_metric_definition_5190e67b5376d2108dbe38f0a0490e2b</name>
        <payload><![CDATA[<?xml version="1.0" encoding="UTF-8"?><record_update sys_domain="global" table="asmt_metric_definition"><asmt_metric_definition action="INSERT_OR_UPDATE"><display>Use a Mid Server</display><metric display_value="As part of the new Service Graph capability, what is the appropriate method ">4990e67b5376d2108dbe38f0a0490e14</metric><normalization_input>0</normalization_input><order/><selected_image/><sys_class_name>asmt_metric_definition</sys_class_name><sys_created_by>admin</sys_created_by><sys_created_on>2025-01-06 20:50:19</sys_created_on><sys_domain>global</sys_domain><sys_domain_path>/</sys_domain_path><sys_id>5190e67b5376d2108dbe38f0a0490e2b</sys_id><sys_mod_count>0</sys_mod_count><sys_name>Use a Mid Server</sys_name><sys_package display_value="Quizard" source="x_560335_quizard">a6b89afc537512108dbe38f0a0490e21</sys_package><sys_policy/><sys_scope display_value="Quizard">a6b89afc537512108dbe38f0a0490e21</sys_scope><sys_update_name>asmt_metric_definition_5190e67b5376d2108dbe38f0a0490e2b</sys_update_name><sys_updated_by>admin</sys_updated_by><sys_updated_on>2025-01-06 20:50:19</sys_updated_on><unselected_image/><value>1</value><x_560335_quizard_is_correct>false</x_560335_quizard_is_correct></asmt_metric_definition><sys_translated_text action="delete_multiple" query="documentkey=5190e67b5376d2108dbe38f0a0490e2b"/></record_update>]]></payload>
        <payload_hash>-2046981422</payload_hash>
        <record_name>Use a Mid Server</record_name>
        <reverted_from/>
        <source>97b0a93b5332d2108dbe38f0a0490e9f</source>
        <source_table>sys_update_set</source_table>
        <state>previous</state>
        <sys_created_by>admin</sys_created_by>
        <sys_created_on>2025-01-06 20:50:19</sys_created_on>
        <sys_id>9990e67b5376d2108dbe38f0a0490e2f</sys_id>
        <sys_mod_count>0</sys_mod_count>
        <sys_recorded_at>1943d61fc4c0000001</sys_recorded_at>
        <sys_updated_by>admin</sys_updated_by>
        <sys_updated_on>2025-01-06 20:50:19</sys_updated_on>
        <type>Assessment Metric Definition</type>
        <update_guid>9d90e67bdc76d2109a2435be55b8842e</update_guid>
        <update_guid_history>9d90e67bdc76d2109a2435be55b8842e:-2046981422</update_guid_history>
    </sys_update_version>
    <sys_metadata_delete action="INSERT_OR_UPDATE">
        <sys_audit_delete display_value="Use a Mid Server">6f73b6f753f6d2108dbe38f0a0490e90</sys_audit_delete>
        <sys_class_name>sys_metadata_delete</sys_class_name>
        <sys_created_by>admin</sys_created_by>
        <sys_created_on>2025-01-06 22:12:56</sys_created_on>
        <sys_db_object display_value="" name="asmt_metric_definition">asmt_metric_definition</sys_db_object>
        <sys_id>1ccd07e9276b4a06a1924348ccdc8d44</sys_id>
        <sys_metadata>5190e67b5376d2108dbe38f0a0490e2b</sys_metadata>
        <sys_mod_count>0</sys_mod_count>
        <sys_name>Use a Mid Server</sys_name>
        <sys_package display_value="Quizard" source="x_560335_quizard">a6b89afc537512108dbe38f0a0490e21</sys_package>
        <sys_parent/>
        <sys_policy/>
        <sys_scope display_value="Quizard">a6b89afc537512108dbe38f0a0490e21</sys_scope>
        <sys_scope_delete display_value="">2defbb397ae84e548cf67a6c7cb06ee4</sys_scope_delete>
        <sys_update_name>asmt_metric_definition_5190e67b5376d2108dbe38f0a0490e2b</sys_update_name>
        <sys_update_version display_value="asmt_metric_definition_5190e67b5376d2108dbe38f0a0490e2b">9990e67b5376d2108dbe38f0a0490e2f</sys_update_version>
        <sys_updated_by>admin</sys_updated_by>
        <sys_updated_on>2025-01-06 22:12:56</sys_updated_on>
    </sys_metadata_delete>
</record_update>
